alu.v
// 32 bit ALU for ARM processor
module alu (input [31:0] a, b, 
            input [2:0] ALUControl,
            output reg [31:0] Result,
            output reg [31:0] Result2,
            output wire [3:0] ALUFlags);
    
    wire negative, zero, carry, overflow;
    wire [31:0] condinvb;
    wire [32:0] sum;
    reg Asign;
    reg Bsign;
    reg [63:0] lres;
    
    assign condinvb = ALUControl[0] ? ~b : b;
    assign sum = a + condinvb + ALUControl;

    always @(*)
    begin
        case (ALUControl[2:0])
            3'b000: Result = sum; 
            3'b001: Result = sum; 
            3'b010: Result = a & b; 
            3'b011: Result = a | b; 
            3'b100: Result = a * b;     //MUL
            3'b101: lres = a * b;       //UMULL
            3'b110: begin               //SMULL
                Asign = a[31];
                Bsign = b[31];
                if(Asign ^ Bsign)begin
                    lres[63] = 1;
                end 
                else begin
                    lres[63] = 0;
                end
                lres[62:0] = a[30:0] * b[30:0];
            end
        endcase
        if (ALUControl[2:0] === 3'b101 || ALUControl[2:0] === 3'b110) begin
                Result = lres[31:0];
                Result2 = lres[63:32];
            end
    end

    assign negative = Result[31];
    assign zero = (Result == 32'b0);
    
    assign carry = (ALUControl[1]==1'b0) & sum[32];
    assign overflow = (ALUControl[1] == 1'b0) & ~(a[31] ^ b[31] ^ ALUControl[0]) & (a[31] ^ sum[31]);
    assign ALUFlags = {negative, zero, carry, overflow};

endmodule

alu_tb.v
module alu_tb();
    reg [31:0] a,b;
    wire [3:0] ALUFlags;
    reg [2:0] ALUControl;
    reg clk, reset;
    reg [102:0] testvector[0:10000000]; // Se cambio la cantidad de bits del testvector para que no haya warnings
    wire [31:0] Result;
    reg [31:0] Result_expected; 
    reg [3:0] ALUFlags_expected;
    reg [31:0] vectornum; 
    reg [4:0] errors; // Solo 5 bits para marcar errores ya que solo hay 21 posibles errores como max.

    alu dut(.a(a),.b(b),.ALUControl(ALUControl),.Result(Result),.ALUFlags(ALUFlags));

    always begin
        clk=1; #5; clk=0; #5;
    end
    
    initial begin
        $readmemh("alu_test_vector.tv", testvector);
        errors=0;
        vectornum=0;
        reset = 1; #17; reset=0;
    end

    always @(posedge clk)
    begin
        ALUFlags_expected=testvector[vectornum][3:0];
        Result_expected=testvector[vectornum][35:4];
        b = testvector[vectornum][67:36];
        a = testvector[vectornum][99:68];
        ALUControl = testvector[vectornum][102:100];
    end

    always @(negedge clk)
    begin
        if  (~reset)
            begin
                if ((Result !== Result_expected) || (ALUFlags !== ALUFlags_expected))
                    begin
                        $display();
                        $display("Testvector: %h", testvector[vectornum]);
                        $display("Vectornum: %d", vectornum);
                        $display();
                        $display("Input a: %h", {a});
                        $display("Input b: %h", {b});
                        $display("Input ALUControl: %b", {ALUControl});
                        $display();
                        $display("Output Result del ALU: %h", Result);
                        $display("Output Result que pusimos en la tabla: %h", Result_expected);
                        $display();
                        $display("Output ALUFlags del ALU: %b", ALUFlags);
                        $display("Output ALUFlags que pusimos en la tabla: %b", ALUFlags_expected);
                        $display();
                        errors=errors+1;
                    end
                vectornum = vectornum+1;

                if (testvector[vectornum][0] === 1'bx)
                    begin
                        $display("Errores Totales:%d",errors);
                        $finish;  
                    end
            end
    end

    initial begin
        $dumpfile("alu.vcd");
        $dumpvars;
    end

endmodule

alu.vcd
$date
	Sun Dec 24 17:58:21 2023
$end
$version
	Icarus Verilog
$end
$timescale
	1s
$end
$scope module alu_tb $end
$var wire 32 ! Result [31:0] $end
$var wire 4 " ALUFlags [3:0] $end
$var reg 3 # ALUControl [2:0] $end
$var reg 4 $ ALUFlags_expected [3:0] $end
$var reg 32 % Result_expected [31:0] $end
$var reg 32 & a [31:0] $end
$var reg 32 ' b [31:0] $end
$var reg 1 ( clk $end
$var reg 5 ) errors [4:0] $end
$var reg 1 * reset $end
$var reg 32 + vectornum [31:0] $end
$scope module dut $end
$var wire 3 , ALUControl [2:0] $end
$var wire 32 - a [31:0] $end
$var wire 32 . b [31:0] $end
$var wire 1 / carry $end
$var wire 1 0 overflow $end
$var wire 1 1 zero $end
$var wire 33 2 sum [32:0] $end
$var wire 1 3 negative $end
$var wire 32 4 condinvb [31:0] $end
$var wire 4 5 ALUFlags [3:0] $end
$var reg 1 6 Asign $end
$var reg 1 7 Bsign $end
$var reg 32 8 Result [31:0] $end
$var reg 32 9 Result2 [31:0] $end
$var reg 64 : lres [63:0] $end
$upscope $end
$upscope $end
$enddefinitions $end
#0
$dumpvars
bx :
bx 9
bx 8
x7
x6
bx 5
bx 4
x3
bx 2
x1
x0
x/
bx .
bx -
bx ,
b0 +
1*
b0 )
1(
bx '
bx &
bx %
bx $
bx #
bx "
bx !
$end
#5
0(
#10
00
03
0/
b100 "
b100 5
11
b0 !
b0 8
b0 2
b0 4
b0 #
b0 ,
b0 &
b0 -
b0 '
b0 .
b0 %
b100 $
1(
#15
0(
#17
0*
#20
1(
#25
b1 +
0(
#30
00
13
b1000 "
b1000 5
01
b11111111111111111111111111111111 !
b11111111111111111111111111111111 8
b11111111111111111111111111111111 2
b11111111111111111111111111111111 4
b11111111111111111111111111111111 '
b11111111111111111111111111111111 .
b11111111111111111111111111111111 %
b1000 $
1(
#35
b10 +
0(
#40
1/
03
b110 "
b110 5
11
b0 !
b0 8
b100000000000000000000000000000000 2
b1 &
b1 -
b0 %
b110 $
1(
#45
b11 +
0(
#50
0/
b0 "
b0 5
01
b100000000 !
b100000000 8
b1 4
b100000000 2
b11111111 &
b11111111 -
b1 '
b1 .
b100000000 %
b0 $
1(
#55
b100 +
0(
#60
1/
b110 "
b110 5
11
b0 !
b0 8
b11111111111111111111111111111111 4
b1 #
b1 ,
b100000000000000000000000000000000 2
b0 &
b0 -
b0 '
b0 .
b0 %
b110 $
1(
#65
b101 +
0(
#70
0/
b0 "
b0 5
01
b1 !
b1 8
b1 2
b0 4
b11111111111111111111111111111111 '
b11111111111111111111111111111111 .
b1 %
b0 $
1(
#75
b110 +
0(
#80
1/
b110 "
b110 5
11
b11111111111111111111111111111110 4
b0 !
b0 8
b100000000000000000000000000000000 2
b1 &
b1 -
b1 '
b1 .
b0 %
b110 $
1(
#85
b111 +
0(
#90
b10 "
b10 5
01
b11111111 !
b11111111 8
b100000000000000000000000011111111 2
b100000000 &
b100000000 -
b11111111 %
b10 $
1(
#95
b1000 +
0(
#100
0/
b11111111111111111111111111111111 4
b1000 "
b1000 5
13
b11111111111111111111111111111111 !
b11111111111111111111111111111111 8
b10 #
b10 ,
b0 2
b11111111111111111111111111111111 &
b11111111111111111111111111111111 -
b11111111111111111111111111111111 '
b11111111111111111111111111111111 .
b11111111111111111111111111111111 %
b1000 $
1(
#105
b1001 +
0(
#110
b0 "
b0 5
03
b10010001101000101011001111000 !
b10010001101000101011001111000 8
b100010010001101000101011001111001 2
b10010001101000101011001111000 4
b10010001101000101011001111000 '
b10010001101000101011001111000 .
b10010001101000101011001111000 %
b0 $
1(
#115
b1010 +
0(
#120
b10001001000100001000100000 !
b10001001000100001000100000 8
b10000111011001010100001100100001 4
b10011001100110011001100110011011 2
b10010001101000101011001111000 &
b10010001101000101011001111000 -
b10000111011001010100001100100001 '
b10000111011001010100001100100001 .
b10001001000100001000100000 %
1(
#125
b1011 +
0(
#130
b100 "
b100 5
11
b0 !
b0 8
b11111111111111111111111111111111 4
b100000000000000000000000000000001 2
b0 &
b0 -
b11111111111111111111111111111111 '
b11111111111111111111111111111111 .
b0 %
b100 $
1(
#135
b1100 +
0(
#140
b0 4
13
b1000 "
b1000 5
01
b11111111111111111111111111111111 !
b11111111111111111111111111111111 8
b11 #
b11 ,
b100000000000000000000000000000010 2
b11111111111111111111111111111111 &
b11111111111111111111111111111111 -
b11111111111111111111111111111111 %
b1000 $
1(
#145
b1101 +
0(
#150
b1111000100110101011110011011110 4
b10010111011101010101011101111001 !
b10010111011101010101011101111001 8
b10001010110011110001001101011001 2
b10010001101000101011001111000 &
b10010001101000101011001111000 -
b10000111011001010100001100100001 '
b10000111011001010100001100100001 .
b10010111011101010101011101111001 %
1(
#155
b1110 +
0(
#160
b0 4
b11111111111111111111111111111111 !
b11111111111111111111111111111111 8
b11 2
b0 &
b0 -
b11111111111111111111111111111111 '
b11111111111111111111111111111111 .
b11111111111111111111111111111111 %
1(
#165
b1111 +
0(
#170
10
03
1/
b111 "
b111 5
11
b10000000000000000000000000000000 4
b0 !
b0 8
b0 #
b0 ,
b100000000000000000000000000000000 2
b10000000000000000000000000000000 &
b10000000000000000000000000000000 -
b10000000000000000000000000000000 '
b10000000000000000000000000000000 .
b0 %
b111 $
1(
#175
b10000 +
0(
#180
00
13
b1010 "
b1010 5
01
b11111111111111111111111111111110 !
b11111111111111111111111111111110 8
b11111111111111111111111111111111 4
b111111111111111111111111111111110 2
b11111111111111111111111111111111 &
b11111111111111111111111111111111 -
b11111111111111111111111111111111 '
b11111111111111111111111111111111 .
b11111111111111111111111111111110 %
b1010 $
1(
#185
b10001 +
0(
#190
10
b1001 "
b1001 5
0/
b1111111111111111111111111111111 4
b11111111111111111111111111111110 2
b1111111111111111111111111111111 &
b1111111111111111111111111111111 -
b1111111111111111111111111111111 '
b1111111111111111111111111111111 .
b1001 $
1(
#195
b10010 +
0(
#200
10
0/
b1001 "
b1001 5
13
b11111111111111111111111111111110 !
b11111111111111111111111111111110 8
b1111111111111111111111111111110 4
b11111111111111111111111111111110 2
b1 #
b1 ,
b10000000000000000000000000000001 '
b10000000000000000000000000000001 .
1(
#205
b10011 +
0(
#210
1/
b10011111111111111111111111111111 4
b11 "
b11 5
03
b110000000000000000000000000000 !
b110000000000000000000000000000 8
b100110000000000000000000000000000 2
b10010000000000000000000000000000 &
b10010000000000000000000000000000 -
b1100000000000000000000000000000 '
b1100000000000000000000000000000 .
b110000000000000000000000000000 %
b11 $
1(
#215
b10100 +
0(
#220
00
b10 "
b10 5
1/
b11111111111111111111111111111010 4
b0 9
b10100 !
b10100 8
b10100 :
b101 #
b101 ,
b100000000000000000000000000000011 2
b100 &
b100 -
b101 '
b101 .
b10100 %
b10 $
1(
#225
b10101 +
0(
#230
b0 "
b0 5
0/
b11111111111111111111111111111011 4
b111 !
b111 8
b11 #
b11 ,
b100000000000000000000000000000001 2
b11 &
b11 -
b100 '
b100 .
b111 %
b0 $
1(
#235
b10110 +
0(
#240
b10 "
b10 5
1/
b1111111111111111111111111111111 4
b1 !
b1 8
b100 #
b100 ,
b100000000000000000000000000000010 2
b1111111111111111111111111111111 &
b1111111111111111111111111111111 -
b1111111111111111111111111111111 '
b1111111111111111111111111111111 .
b1 %
b10 $
1(
#245
b10111 +
0(
#250
b1010 "
b1010 5
13
b11111111111111111111111111111111 !
b11111111111111111111111111111111 8
b100000000000000000000000000000100 2
b10000000000000000000000000000001 4
b10000000000000000000000000000001 '
b10000000000000000000000000000001 .
b11111111111111111111111111111111 %
b1010 $
1(
#255
b11000 +
0(
#260
0/
03
b100 "
b100 5
11
b0 !
b0 8
b1100000000000000000000000000000 4
b11110000000000000000000000000100 2
b10010000000000000000000000000000 &
b10010000000000000000000000000000 -
b1100000000000000000000000000000 '
b1100000000000000000000000000000 .
b0 %
b100 $
1(
#265
b11001 +
0(
